ab_test_toolkit/__init__.py
ab_test_toolkit/_modidx.py
ab_test_toolkit/analyze.py
ab_test_toolkit/generator.py
ab_test_toolkit/plotting.py
ab_test_toolkit/power.py
ab_test_toolkit/wrappers.py
ab_test_toolkit-0.0.15.dist-info/LICENSE
ab_test_toolkit-0.0.15.dist-info/METADATA
ab_test_toolkit-0.0.15.dist-info/WHEEL
ab_test_toolkit-0.0.15.dist-info/entry_points.txt
ab_test_toolkit-0.0.15.dist-info/top_level.txt
ab_test_toolkit-0.0.15.dist-info/RECORD
