Metadata-Version: 2.1
Name: ab-test-toolkit
Version: 0.0.15
Summary: Toolkit to simulate and analyze AB tests
Home-page: https://github.com/k111git/ab-test-toolkit
Author: Kolja
Author-email: 
License: Apache Software License 2.0
Keywords: python experimentation AB-testing
Platform: UNKNOWN
Classifier: Development Status :: 4 - Beta
Classifier: Intended Audience :: Developers
Classifier: Natural Language :: English
Classifier: Programming Language :: Python :: 3.7
Classifier: Programming Language :: Python :: 3.8
Classifier: Programming Language :: Python :: 3.9
Classifier: Programming Language :: Python :: 3.10
Classifier: License :: OSI Approved :: Apache Software License
Requires-Python: >=3.7
Requires-Dist: fastcore
Requires-Dist: pandas
Requires-Dist: black
Requires-Dist: jupyter-black
Requires-Dist: numpy
Requires-Dist: scipy
Requires-Dist: plotly
Requires-Dist: bayesian-testing
Requires-Dist: statsmodels
Provides-Extra: dev
